simplefit/__init__.py
simplefit/classifier.py
simplefit/cleaner.py
simplefit/eda.py
simplefit/regressor.py
simplefit-0.1.5.dist-info/LICENSE
simplefit-0.1.5.dist-info/WHEEL
simplefit-0.1.5.dist-info/METADATA
simplefit-0.1.5.dist-info/RECORD
