Metadata-Version: 2.1
Name: simplefit
Version: 0.1.5
Summary: Package that will clean the data, do basic EDA and provide an insight to basic models, LR and ridge
License: MIT
Author: Reza Zoe Navya Sanchit
Requires-Python: >=3.9,<4.0
Classifier: License :: OSI Approved :: MIT License
Classifier: Programming Language :: Python :: 3
Classifier: Programming Language :: Python :: 3.10
Classifier: Programming Language :: Python :: 3.9
Requires-Dist: altair (>=4.2.0,<5.0.0)
Requires-Dist: altair-data-server (>=0.4.1,<0.5.0)
Requires-Dist: altair-saver (>=0.5.0,<0.6.0)
Requires-Dist: notebook (>=6.4.7,<7.0.0)
Requires-Dist: pandas (>=1.3.5,<2.0.0)
Requires-Dist: python-semantic-release (>=7.24.0,<8.0.0)
Requires-Dist: sklearn (>=0.0,<0.1)
Requires-Dist: vega (==1.3.0)
Requires-Dist: vega-datasets (>=0.9.0,<0.10.0)
